setup.py
padlock/__init__.py
padlock/interface_utils.py
padlock.egg-info/PKG-INFO
padlock.egg-info/SOURCES.txt
padlock.egg-info/dependency_links.txt
padlock.egg-info/requires.txt
padlock.egg-info/top_level.txt