Metadata-Version: 1.1
Name: padlock
Version: 0.0.2
Summary: A lock library with multiple backends
Home-page: http://github.com/samuraisam/padlock
Author: Samuel Sutch
Author-email: samuel.sutch@gmail.com
License: UNKNOWN
Platform: UNKNOWN
Classifier: Development Status :: 3 - Alpha
Classifier: Intended Audience :: Developers
Classifier: License :: OSI Approved :: Apache Software License
Classifier: Operating System :: OS Independent
Classifier: Programming Language :: Python
Classifier: Programming Language :: Python :: 2.7
